eu_consultations/__init__.py
eu_consultations/consultation_data.py
eu_consultations/extract_filetext.py
eu_consultations/scrape.py
eu_consultations/utils_scraping.py
eu_consultations-0.3.0.dist-info/licenses/LICENSE
eu_consultations-0.3.0.dist-info/METADATA
eu_consultations-0.3.0.dist-info/WHEEL
eu_consultations-0.3.0.dist-info/top_level.txt
eu_consultations-0.3.0.dist-info/RECORD
