Metadata-Version: 2.4
Name: eu-consultations
Version: 0.3.0
Summary: A Python package for scraping textual data from EU public consultations
Author-email: Mario Angst <mario.angst@uzh.ch>
License-Expression: MIT
Project-URL: repository, https://github.com/marioangst/eu_consultations
Requires-Python: >=3.12
License-File: LICENSE
Requires-Dist: aiohttp-retry>=2.9.1
Requires-Dist: asyncio>=3.4.3
Requires-Dist: bson>=0.5.10
Requires-Dist: httpx>=0.28.1
Requires-Dist: loguru>=0.7.3
Requires-Dist: pandas>=2.2.3
Requires-Dist: pytest>=8.3.5
Requires-Dist: srsly>=2.5.1
Requires-Dist: dataclasses>=0.8
Requires-Dist: dataclass-wizard>=0.35.0
Requires-Dist: tqdm>=4.67.1
Requires-Dist: docling>=2.26.0
Requires-Dist: pypdf>=5.4.0
Dynamic: license-file
